Metadata-Version: 1.1
Name: usernamegen
Version: 0.1.1
Summary: Genrate usernames with a Markov chain based on a wordlist
Home-page: https://github.com/stylesuxx/usernamegen/
Author: Chris Landa
Author-email: stylesuxx@gmail.com
License: MIT
Download-URL: https://github.com/stylesuxx/usernamegen/tarball/0.1.1
Platform: UNKNOWN
Classifier: Programming Language :: Python
Classifier: Programming Language :: Python :: 2.7
Classifier: License :: OSI Approved :: MIT License
Classifier: Intended Audience :: Developers
Classifier: Operating System :: OS Independent
Classifier: Topic :: Software Development :: Libraries :: Python Modules
Classifier: Topic :: Internet :: WWW/HTTP
